bq_easy_zfullio/__init__.py
bq_easy_zfullio/big_query.py
bq_easy_zfullio-1.0.1.dist-info/LICENSE
bq_easy_zfullio-1.0.1.dist-info/METADATA
bq_easy_zfullio-1.0.1.dist-info/WHEEL
bq_easy_zfullio-1.0.1.dist-info/RECORD
