Metadata-Version: 2.1
Name: bq_easy_zfullio
Version: 1.0.1
Summary: Простой экспорт из Pandas Dataframe в BQ
Author: viktor
Author-email: vi.dave@yandex.ru
Requires-Python: >=3.10
Classifier: Programming Language :: Python :: 3
Classifier: Programming Language :: Python :: 3.10
Classifier: Programming Language :: Python :: 3.11
Classifier: Programming Language :: Python :: 3.12
Requires-Dist: google-cloud-bigquery (>=3,<4)
